juviz/__init__.py
juviz/assets/FZJ_Logo.svg
juviz/assets/__init__.py
juviz/widgets/__init__.py
juviz/widgets/juviz_controller.py
juviz_app-0.1.2.dist-info/LICENSE
juviz_app-0.1.2.dist-info/METADATA
juviz_app-0.1.2.dist-info/WHEEL
juviz_app-0.1.2.dist-info/top_level.txt
juviz_app-0.1.2.dist-info/RECORD
