Metadata-Version: 2.1
Name: juviz-app
Version: 0.1.2
Summary: Default trame App for JuViz
Author: Jonathan Windgassen
Author-email: j.windgassen@fz-juelich.de
License: BSD License
Keywords: Python,Interactive,Web,Application,Framework
Classifier: Programming Language :: Python :: 3 :: Only
Classifier: Environment :: Web Environment
Classifier: License :: OSI Approved :: BSD License
Classifier: Natural Language :: English
Classifier: Operating System :: OS Independent
Classifier: Framework :: Jupyter
Classifier: Topic :: Software Development :: Libraries :: Application Frameworks
Classifier: Topic :: Software Development :: Libraries :: Python Modules
License-File: LICENSE
Requires-Dist: pv-visualizer
Requires-Dist: wslink (>=1.11.1)
